penify_hook/api_client.py
penify_hook/commit_analyzer.py
penify_hook/file_analyzer.py
penify_hook/folder_analyzer.py
penify_hook/git_analyzer.py
penify_hook/main.py
penify_hook/utils.py
penify_cli-0.1.5.dist-info/METADATA
penify_cli-0.1.5.dist-info/WHEEL
penify_cli-0.1.5.dist-info/entry_points.txt
penify_cli-0.1.5.dist-info/top_level.txt
penify_cli-0.1.5.dist-info/RECORD
