Metadata-Version: 2.1
Name: penify-cli
Version: 0.1.5
Summary: A penify cli tool to generate Documentation, Commit-summary and  Hooks to automate git workflows.
Home-page: https://github.com/SingularityX-ai/penify-cli
Author: Suman Saurabh
Author-email: ss.sumansaurabh92@gmail.com
Classifier: Programming Language :: Python :: 3
Classifier: License :: OSI Approved :: MIT License
Classifier: Operating System :: OS Independent
Requires-Python: >=3.6
Requires-Dist: requests
Requires-Dist: tqdm
Requires-Dist: GitPython
